atx_mainframe_dependency_manager/__init__.py
atx_mainframe_dependency_manager/dependency_manager.py
atx_mainframe_dependency_manager/py.typed
atx_mainframe_dependency_manager/server.py
atx_mainframe_dependency_manager/tools/__init__.py
atx_mainframe_dependency_manager/tools/dependency_tools.py
atx_mainframe_dependency_manager/tools/source_code_tools.py
atx_mainframe_dependency_manager-0.1.6.dist-info/licenses/LICENSE
atx_mainframe_dependency_manager-0.1.6.dist-info/METADATA
atx_mainframe_dependency_manager-0.1.6.dist-info/WHEEL
atx_mainframe_dependency_manager-0.1.6.dist-info/entry_points.txt
atx_mainframe_dependency_manager-0.1.6.dist-info/top_level.txt
atx_mainframe_dependency_manager-0.1.6.dist-info/RECORD
