Metadata-Version: 2.4
Name: atx-mainframe-dependency-manager
Version: 0.1.6
Summary: MCP server for managing mainframe component dependencies and relationships
Author-email: Arunkumar Selvam <aruninfy123@gmail.com>
License: MIT
Project-URL: Homepage, https://github.com/arunkumars-mf/atx-mainframe-dependency-manager
Project-URL: Bug Reports, https://github.com/arunkumars-mf/atx-mainframe-dependency-manager/issues
Project-URL: Source, https://github.com/arunkumars-mf/atx-mainframe-dependency-manager
Keywords: mainframe,dependency,management,mcp,cobol,jcl,copybook,cross-platform
Classifier: Development Status :: 3 - Alpha
Classifier: Intended Audience :: Developers
Classifier: Topic :: Software Development :: Libraries :: Python Modules
Classifier: Topic :: System :: Systems Administration
Classifier: Programming Language :: Python :: 3
Classifier: Programming Language :: Python :: 3.8
Classifier: Programming Language :: Python :: 3.9
Classifier: Programming Language :: Python :: 3.10
Classifier: Programming Language :: Python :: 3.11
Classifier: Programming Language :: Python :: 3.12
Classifier: License :: OSI Approved :: MIT License
Classifier: Operating System :: OS Independent
Classifier: Operating System :: Microsoft :: Windows
Classifier: Operating System :: POSIX :: Linux
Classifier: Operating System :: MacOS
Requires-Python: >=3.8
License-File: LICENSE
Requires-Dist: mcp>=1.0.0
Requires-Dist: pydantic>=2.0.0
Requires-Dist: anyio>=3.0.0
Requires-Dist: pathlib2>=2.3.0; python_version < "3.4"
Dynamic: license-file
